odoo/addons/business_requirement_sale_timesheet/README.rst
odoo/addons/business_requirement_sale_timesheet/__init__.py
odoo/addons/business_requirement_sale_timesheet/__manifest__.py
odoo/addons/business_requirement_sale_timesheet/i18n/business_requirement_sale_timesheet.pot
odoo/addons/business_requirement_sale_timesheet/models/__init__.py
odoo/addons/business_requirement_sale_timesheet/models/project_task.py
odoo/addons/business_requirement_sale_timesheet/readme/CONTRIBUTORS.rst
odoo/addons/business_requirement_sale_timesheet/readme/CREDITS.rst
odoo/addons/business_requirement_sale_timesheet/readme/DESCRIPTION.rst
odoo/addons/business_requirement_sale_timesheet/readme/USAGE.rst
odoo/addons/business_requirement_sale_timesheet/static/description/icon.png
odoo/addons/business_requirement_sale_timesheet/static/description/index.html
odoo/addons/business_requirement_sale_timesheet/tests/__init__.py
odoo/addons/business_requirement_sale_timesheet/tests/test_business_requirement_sale_timesheet.py
odoo/addons/business_requirement_sale_timesheet/views/project_task.xml
odoo11_addon_business_requirement_sale_timesheet-11.0.1.1.0.99.dev3.dist-info/METADATA
odoo11_addon_business_requirement_sale_timesheet-11.0.1.1.0.99.dev3.dist-info/WHEEL
odoo11_addon_business_requirement_sale_timesheet-11.0.1.1.0.99.dev3.dist-info/top_level.txt
odoo11_addon_business_requirement_sale_timesheet-11.0.1.1.0.99.dev3.dist-info/RECORD
